dgbowl_schemas/__init__.py
dgbowl_schemas/dgpost/__init__.py
dgbowl_schemas/dgpost/recipe/__init__.py
dgbowl_schemas/dgpost/recipe_1_0/__init__.py
dgbowl_schemas/dgpost/recipe_1_0/extract.py
dgbowl_schemas/dgpost/recipe_1_0/load.py
dgbowl_schemas/dgpost/recipe_1_0/plot.py
dgbowl_schemas/dgpost/recipe_1_0/save.py
dgbowl_schemas/dgpost/recipe_1_0/transform.py
dgbowl_schemas/dgpost/recipe_2_1/__init__.py
dgbowl_schemas/dgpost/recipe_2_1/extract.py
dgbowl_schemas/dgpost/recipe_2_1/load.py
dgbowl_schemas/dgpost/recipe_2_1/pivot.py
dgbowl_schemas/dgpost/recipe_2_1/plot.py
dgbowl_schemas/dgpost/recipe_2_1/save.py
dgbowl_schemas/dgpost/recipe_2_1/transform.py
dgbowl_schemas/dgpost/recipe_2_2/__init__.py
dgbowl_schemas/tomato/__init__.py
dgbowl_schemas/tomato/payload/__init__.py
dgbowl_schemas/tomato/payload_0_1/__init__.py
dgbowl_schemas/tomato/payload_0_1/method.py
dgbowl_schemas/tomato/payload_0_1/sample.py
dgbowl_schemas/tomato/payload_0_1/tomato.py
dgbowl_schemas/tomato/payload_0_2/__init__.py
dgbowl_schemas/tomato/payload_0_2/method.py
dgbowl_schemas/tomato/payload_0_2/sample.py
dgbowl_schemas/tomato/payload_0_2/tomato.py
dgbowl_schemas/tomato/payload_1_0/__init__.py
dgbowl_schemas/tomato/payload_1_0/sample.py
dgbowl_schemas/tomato/payload_1_0/settings.py
dgbowl_schemas/tomato/payload_1_0/task.py
dgbowl_schemas/tomato/payload_2_0/__init__.py
dgbowl_schemas/tomato/payload_2_0/sample.py
dgbowl_schemas/tomato/payload_2_0/settings.py
dgbowl_schemas/tomato/payload_2_0/task.py
dgbowl_schemas/tomato/payload_2_1/__init__.py
dgbowl_schemas/tomato/payload_2_1/sample.py
dgbowl_schemas/tomato/payload_2_1/settings.py
dgbowl_schemas/tomato/payload_2_1/task.py
dgbowl_schemas/yadg/__init__.py
dgbowl_schemas/yadg/dataschema/__init__.py
dgbowl_schemas/yadg/dataschema_4_0/__init__.py
dgbowl_schemas/yadg/dataschema_4_0/externaldate.py
dgbowl_schemas/yadg/dataschema_4_0/input.py
dgbowl_schemas/yadg/dataschema_4_0/metadata.py
dgbowl_schemas/yadg/dataschema_4_0/parameters.py
dgbowl_schemas-124.dist-info/METADATA
dgbowl_schemas-124.dist-info/WHEEL
dgbowl_schemas-124.dist-info/top_level.txt
dgbowl_schemas-124.dist-info/RECORD
